refs_nb/__init__.py
refs_nb/inference.py
refs_nb/text_classifier_pipeline_hashed.joblib
refs_nb-1.0.0.dist-info/LICENSE
refs_nb-1.0.0.dist-info/METADATA
refs_nb-1.0.0.dist-info/WHEEL
refs_nb-1.0.0.dist-info/top_level.txt
refs_nb-1.0.0.dist-info/RECORD
