Metadata-Version: 2.1
Name: refs-nb
Version: 1.0.0
Summary: Fast Naive Bayes classifier for reference detection in scientific text.
Author-email: Yuanzhou Cai <80858000+yuanjua@users.noreply.github.com>
License: Apache-2.0
Classifier: Programming Language :: Python :: 3
Classifier: License :: OSI Approved :: Apache Software License
Classifier: Operating System :: OS Independent
Classifier: Intended Audience :: Science/Research
Requires-Python: >=3.8
License-File: LICENSE
Requires-Dist: joblib >=1.1.1
Requires-Dist: scikit-learn >=1.2.2
